alumathpeergroup17/__init__.py
alumathpeergroup17/matrixComputation.py
alumathpeergroup17-0.1.4.dist-info/METADATA
alumathpeergroup17-0.1.4.dist-info/WHEEL
alumathpeergroup17-0.1.4.dist-info/top_level.txt
alumathpeergroup17-0.1.4.dist-info/RECORD
