Metadata-Version: 2.4
Name: alumathpeergroup17
Version: 0.1.4
Summary: A basic matrix computation library for addition, subtraction, and multiplication.
Author: WilsonsNavid
Author-email: wadotiwawil@gmail.com
License: MIT
Keywords: matrix addition subtraction multiplication linear-algebra
Classifier: Programming Language :: Python :: 3
Classifier: License :: OSI Approved :: MIT License
Classifier: Operating System :: OS Independent
Classifier: Topic :: Scientific/Engineering :: Mathematics
Requires-Python: >=3.6
Dynamic: author
Dynamic: author-email
Dynamic: classifier
Dynamic: description
Dynamic: description-content-type
Dynamic: keywords
Dynamic: license
Dynamic: requires-python
Dynamic: summary
